py_transmuter/__init__.py
py_transmuter/self_inspector.py
py_transmuter/dictionaries/__init__.py
py_transmuter/dictionaries/aggregator.py
py_transmuter/dictionaries/mapper.py
py_transmuter/models/__init__.py
py_transmuter/models/aggregator.py
py_transmuter/models/mapper.py
py_transmuter/models/types.py
py_transmuter/models/utils.py
py_transmuter-0.2.0.dist-info/METADATA
py_transmuter-0.2.0.dist-info/WHEEL
py_transmuter-0.2.0.dist-info/licenses/LICENSE
py_transmuter-0.2.0.dist-info/RECORD
