Metadata-Version: 2.3
Name: py-transmuter
Version: 0.2.0
Summary: A library that facilitates mapping and aggregating objects from one model to another
Project-URL: Homepage, https://github.com/RodrigoDeRosa/py-transmuter
Project-URL: Issues, https://github.com/RodrigoDeRosa/py-transmuter/issues
Author-email: Rodrigo De Rosa <rodrigoderosa15@gmail.com>
License: MIT License
License-File: LICENSE
Classifier: Development Status :: 3 - Alpha
Classifier: Framework :: Pydantic :: 2
Classifier: Intended Audience :: Developers
Classifier: License :: OSI Approved :: MIT License
Classifier: Programming Language :: Python :: 3.12
Requires-Python: >=3.12.0
